{
  "parrafos_gratis": 14,
  "resumen": "JBS S.A. es la mayor procesadora de proteinas animales del mundo, con operaciones en carne vacuna, aves, cerdo, cordero y pescado en mas de 180 paises. En FY2024 genero ingresos de USD 77.2B con EBITDA ajustado de USD 7.2B y recupero rentabilidad con margen neto del 2.5%. Cotiza en NYSE como JBS N.V. con valuacion atractiva de 7.9x P/E y 6.1x EV/EBITDA, con FCF yield del 20%.",
  "descripcion": "JBS opera 7 segmentos: Brazil, Seara, Beef North America, Pork USA, Pilgrims Pride, Australia y Otros. Su moat se basa en escala operativa incomparable (#1 carne bovina global, #1 aves global, #2 cerdo global), diversificacion en 180 paises, marcas Swift, Seara, Friboi y Pilgrim, y capacidad logistica global. En 2025 completo reestructuracion hacia JBS N.V. con listado NYSE.",
  "tabla": {
    "headers": [
      "Metrica",
      "FY2021",
      "FY2022",
      "FY2023",
      "FY2024",
      "FY2025e",
      "Var. YoY"
    ],
    "rows": [
      [
        "Revenue (B USD)",
        "65.0",
        "72.6",
        "72.9",
        "77.2",
        "~88.3",
        "+5.8%"
      ],
      [
        "Utilidad Neta (B USD)",
        "3.82",
        "3.14",
        "-0.13",
        "1.97",
        "~4.0",
        "+NM"
      ],
      [
        "Margen Neto",
        "5.9%",
        "4.3%",
        "-0.2%",
        "2.5%",
        "~4.5%",
        "+2.7pp"
      ],
      [
        "EBITDA Adj. (B USD)",
        "7.66",
        "6.72",
        "3.46",
        "7.19",
        "~9.0",
        "+108%"
      ],
      [
        "FCF (B USD)",
        "2.22",
        "0.41",
        "0.88",
        "2.75",
        "~3.5",
        "+213%"
      ],
      [
        "EPS Diluido",
        "1.54",
        "1.34",
        "-0.09",
        "0.80",
        "~1.68",
        "+NM"
      ],
      [
        "Deuda Neta (B USD)",
        "~13.0",
        "~15.8",
        "~14.4",
        "13.7",
        "~13.0",
        "-0.7B"
      ]
    ]
  },
  "kpis": [
    {
      "label": "P/E Trailing",
      "value": "7.9x",
      "signal": "green",
      "note": "vs. sector ~15x",
      "precio_base": 12.74,
      "precio_fecha": "2026-05-26",
      "fundamento": {
        "tipo": "eps_ttm",
        "valor": 1.62
      }
    },
    {
      "label": "P/E Forward",
      "value": "7.6x",
      "signal": "green",
      "precio_base": 12.74,
      "precio_fecha": "2026-05-26",
      "fundamento": {
        "tipo": "eps_fwd",
        "valor": 1.685
      }
    },
    {
      "label": "EV/EBITDA",
      "value": "6.1x",
      "signal": "green",
      "precio_base": 12.74,
      "precio_fecha": "2026-05-26",
      "fundamento": {
        "tipo": "ev_ebitda",
        "ebitda_b": 7.192,
        "shares_m": 776,
        "deuda_neta_b": 13.7
      }
    },
    {
      "label": "P/FCF",
      "value": "5.0x",
      "signal": "green",
      "precio_base": 12.74,
      "precio_fecha": "2026-05-26",
      "fundamento": {
        "tipo": "p_fcf",
        "fcf_b": 2.75,
        "shares_m": 776
      }
    },
    {
      "label": "Deuda Neta/EBITDA",
      "value": "1.9x",
      "signal": "yellow"
    },
    {
      "label": "ROE",
      "value": "24.2%",
      "signal": "green"
    },
    {
      "label": "ROIC",
      "value": "~12%",
      "signal": "yellow"
    }
  ],
  "chart_ingresos": {
    "unit": "B USD",
    "data": [
      {
        "label": "FY2021",
        "revenue": 65,
        "utilidad": 3.82
      },
      {
        "label": "FY2022",
        "revenue": 72.6,
        "utilidad": 3.14
      },
      {
        "label": "FY2023",
        "revenue": 72.9,
        "utilidad": -0.13
      },
      {
        "label": "FY2024",
        "revenue": 77.2,
        "utilidad": 1.97
      }
    ],
    "series": [
      {
        "key": "revenue",
        "name": "Revenue"
      },
      {
        "key": "utilidad",
        "name": "Utilidad Neta"
      }
    ]
  },
  "chart_margenes": {
    "data": [
      {
        "label": "FY2021",
        "bruto": 18.9,
        "operativo": 9.2,
        "neto": 5.9
      },
      {
        "label": "FY2022",
        "bruto": 15.9,
        "operativo": 6.6,
        "neto": 4.3
      },
      {
        "label": "FY2023",
        "bruto": 10.9,
        "operativo": 1.5,
        "neto": -0.2
      },
      {
        "label": "FY2024",
        "bruto": 15,
        "operativo": 5.7,
        "neto": 2.5
      }
    ],
    "series": [
      {
        "key": "bruto",
        "name": "Margen Bruto"
      },
      {
        "key": "operativo",
        "name": "Margen Operativo"
      },
      {
        "key": "neto",
        "name": "Margen Neto"
      }
    ]
  },
  "capital_allocation": {
    "items": [
      {
        "label": "Dividendos",
        "value": "~0.8B USD",
        "nota": "USD 0.48/accion en FY2024; politica de 25% del beneficio neto por ley brasilena"
      },
      {
        "label": "Capex",
        "value": "1.5B USD",
        "nota": "66% mantenimiento, 34% expansion de capacidad en FY2024"
      },
      {
        "label": "Recompras",
        "value": "0B USD",
        "nota": "No se realizaron recompras en FY2024; FY2022 incluyo USD 552M de buybacks"
      },
      {
        "label": "M&A",
        "value": "~0B USD",
        "nota": "Actividad M&A pausada en FY2024; fase de consolidacion post-adquisiciones"
      }
    ]
  },
  "comparacion_sector": {
    "headers": [
      "Metrica",
      "JBS TTM",
      "Sector ref.",
      "Posicion relativa"
    ],
    "rows": [
      [
        "Gross Margin",
        "15.0%",
        "~14%",
        "En linea con sector carnico"
      ],
      [
        "Margen Operativo",
        "5.7%",
        "~4%",
        "Por encima del sector"
      ],
      [
        "Revenue Growth",
        "+5.8%",
        "~3%",
        "Por encima del sector"
      ],
      [
        "P/E Forward",
        "7.6x",
        "~15x",
        "Descuento significativo vs. sector"
      ],
      [
        "ROIC",
        "~12%",
        "~10%",
        "Por encima del sector"
      ]
    ]
  },
  "deterioro": {
    "veredicto": "JBS muestra recuperacion solida en FY2024 tras el annus horribilis de FY2023; EBITDA se duplico y FCF alcanzo USD 2.75B.",
    "analisis": "FY2023 fue contraccion excepcional: ciclo negativo de bovino USA, presion de costos de insumos y tipo de cambio adverso. FY2024 confirma recuperacion estructural con margenes en expansion. Deuda neta de 13.7B es manejable con ND/EBITDA de 1.9x.",
    "items": [
      {
        "metrica": "Revenue YoY",
        "valor": "+5.8%",
        "status": "ok"
      },
      {
        "metrica": "Margen Bruto",
        "valor": "15.0%",
        "status": "ok"
      },
      {
        "metrica": "Margen Operativo",
        "valor": "5.7%",
        "status": "warn"
      },
      {
        "metrica": "Margen Neto",
        "valor": "2.5%",
        "status": "warn"
      },
      {
        "metrica": "FCF YoY",
        "valor": "+213%",
        "status": "ok"
      },
      {
        "metrica": "Deuda Neta",
        "valor": "13.7B",
        "status": "warn"
      }
    ]
  },
  "flags": [
    {
      "level": "green",
      "title": "Valuacion extremadamente barata",
      "impact": "Alto",
      "evidence": "P/E 7.9x, EV/EBITDA 6.1x, P/FCF 5.0x. Descuento del 50%+ vs. sector alimentos ~15-20x EV/EBITDA",
      "context": "El mercado penaliza el stock por riesgo Brasil y volatilidad ciclica. A estos precios el upside es significativo si los multiples se normalizan."
    },
    {
      "level": "green",
      "title": "Liderazgo mundial en proteinas",
      "impact": "Alto",
      "evidence": "#1 carne bovina global, #1 aves global, #2 cerdo global por capacidad. 320,000 clientes en 180 paises",
      "context": "Escala incomparable con barrera de entrada casi insuperable por requerimientos de capital. Posicion consolidada con +20 anos de adquisiciones."
    },
    {
      "level": "green",
      "title": "FCF recovery excepcional FY2024",
      "impact": "Alto",
      "evidence": "FCF de USD 2.75B en FY2024 vs USD 0.88B en FY2023 (+213% YoY). FCF yield ~20% sobre market cap",
      "context": "Recuperacion impulsada por normalizacion del ciclo bovino USA y mejora de margenes en Seara y Pilgrims. Capacidad para reducir deuda agresivamente."
    },
    {
      "level": "yellow",
      "title": "Apalancamiento moderado-alto",
      "impact": "Medio",
      "evidence": "Deuda neta de USD 13.7B, ND/EBITDA de 1.9x en FY2024",
      "context": "Mejoro vs. 4.2x en FY2023. Vencimientos escalonados hasta mid-2032. No es riesgo inmediato pero limita buybacks y dividendos extraordinarios."
    },
    {
      "level": "yellow",
      "title": "Margenes ciclicos y volatiles",
      "impact": "Medio",
      "evidence": "Margen neto oscilo entre -0.2% (FY2023) y 5.9% (FY2021) segun ciclo bovino USA",
      "context": "La proteina animal es commodity ciclica. El ciclo bovino USA se normaliza lentamente. Seara y aves compensan parte pero no eliminan la volatilidad."
    },
    {
      "level": "red",
      "title": "Riesgo regulatorio y gobernanza Brasil",
      "impact": "Alto",
      "evidence": "Investigacion J&F Leniency activa; familia Batista controla ~40% con estructura de voto concentrada",
      "context": "Historial de escandalo de corrupcion 2017-2018. Reestructuracion a JBS N.V. busca separar riesgo juridico Brasil. Persisten riesgos de litigios y multas."
    }
  ],
  "score": {
    "score": 7.2,
    "max": 10,
    "items": [
      {
        "label": "Poder de fijacion de precios",
        "score": 6,
        "max": 10
      },
      {
        "label": "Crecimiento de revenue",
        "score": 7,
        "max": 10
      },
      {
        "label": "Calidad de margenes",
        "score": 7,
        "max": 10
      },
      {
        "label": "Solidez del balance",
        "score": 7,
        "max": 10
      },
      {
        "label": "Generacion de FCF",
        "score": 9,
        "max": 10
      }
    ]
  },
  "analisis_cualitativo": {
    "estrategia": "JBS ejecuta estrategia de consolidacion global en proteinas animales: adquisiciones para ganar escala, optimizacion de costos e integracion vertical. En 2025 completo reestructuracion hacia JBS N.V. con cotizacion NYSE, separando el negocio del riesgo juridico Brasil y abriendo acceso a capital institucional americano. La estrategia de marcas premium busca reducir exposicion a volatilidad de commodities.",
    "ventajas": "Escala sin precedentes en la industria carnica global; diversificacion geografica y de especies reduce concentracion de riesgo; presencia en paises exportadores lideres con acceso a mercados asiaticos; marcas reconocidas con poder de pricing en categorias value-added; alta eficiencia operativa por economias de escala.",
    "debilidades": "Margenes netos bajos y ciclicos inherentes al negocio de proteinas; apalancamiento que limita flexibilidad financiera; exposicion cambiaria multidivisa compleja; dependencia de insumos agricolas volatiles; riesgo reputacional y regulatorio heredado del escandalo J&F.",
    "riesgos": [
      "Ciclo bovino USA: compresion de oferta de ganado puede mantenerse hasta 2026-2027 presionando margenes de Beef NA",
      "Restricciones sanitarias o arancelarias a exportaciones desde Brasil/Australia hacia China o Japon",
      "Litigios J&F Leniency: multas adicionales o escandalo reputacional podrian impactar flujo de caja y acceso a credito",
      "Fortalecimiento de BRL o AUD vs USD erosiona resultados consolidados reportados en dolares",
      "Disrupciones en cadena de suministro de granos y soya por eventos climaticos extremos"
    ],
    "inversiones_estrategicas": "Capex de USD 1.5B en FY2024: expansion de planta de especialidades en Columbia SC, modernizacion de facilidades Seara Brasil y expansion de capacidad avicola. Inversion en tecnologia de procesamiento para mejorar rendimientos. Exploracion de proteinas alternativas bajo marca Incrivel (plant-based) en Brasil."
  },
  "verdict": {
    "status": "Comprar con Conviccion",
    "score": "7.2/10",
    "color": "green",
    "metrics": [
      {
        "label": "Revenue FY2024",
        "value": "USD 77.2B"
      },
      {
        "label": "EBITDA Adj.",
        "value": "USD 7.2B"
      },
      {
        "label": "FCF FY2024",
        "value": "USD 2.75B"
      },
      {
        "label": "P/E Forward",
        "value": "7.6x"
      },
      {
        "label": "EV/EBITDA",
        "value": "6.1x"
      }
    ],
    "bullets": [
      {
        "text": "**Valuacion de ganga** - Con P/E de 7.9x y EV/EBITDA de 6.1x, JBS cotiza con descuento del 50%+ frente a peers globales de alimentos y ofrece FCF yield del 20%, creando perfil de retorno asimetrico excepcional.",
        "type": "pro"
      },
      {
        "text": "**Liderazgo estructural en proteinas** - JBS es la empresa #1 global en carne bovina y aves por capacidad. Escala inexpugnable consolidada con mas de 20 anos de adquisiciones estrategicas y USD 19B+ de deuda total como reflejo de la escala alcanzada.",
        "type": "pro"
      },
      {
        "text": "**Recovery de EBITDA y FCF confirmado** - EBITDA ajustado se duplico a USD 7.2B en FY2024 vs USD 3.5B en FY2023, con FCF de USD 2.75B que permite reduccion acelerada de deuda y mayor retorno de capital en 2025-2026.",
        "type": "pro"
      },
      {
        "text": "**Reestructuracion a NYSE como catalizador** - Listado como JBS N.V. en NYSE abre la accion a capital institucional americano antes excluido, y puede ser catalizador para re-rating del multiplo hacia sector.",
        "type": "pro"
      },
      {
        "text": "**Riesgo ciclico y de gobernanza** - Los margenes son inherentemente ciclicos (margen neto entre -0.2% y 5.9% en 4 anos) y el historial de la familia Batista requiere prima de riesgo permanente que puede limitar re-rating del multiplo.",
        "type": "con"
      }
    ]
  },
  "conclusion": {
    "items": [
      {
        "label": "Ingresos",
        "texto": "Revenue de USD 77.2B en FY2024 (+5.8% YoY), impulsado por Seara Brasil, Pilgrims Pride y recuperacion parcial de Beef North America. TTM segun Yahoo supera USD 88B, sugiriendo aceleracion adicional en 2025."
      },
      {
        "label": "Margenes",
        "texto": "Margen bruto recuperado al 15.0% (vs 10.9% en FY2023), margen operativo al 5.7% y margen neto del 2.5%. La mejora refleja normalizacion del ciclo bovino USA y expansion de categorias value-added en Seara y Pilgrims Pride."
      },
      {
        "label": "Generacion de caja",
        "texto": "OCF de USD 4.2B y FCF de USD 2.75B en FY2024, el mejor nivel desde FY2021. FCF yield del ~20% sobre market cap actual es excepcional. Liquidez solida con USD 5.6B en caja y USD 3.4B en lineas revolving disponibles."
      },
      {
        "label": "Balance",
        "texto": "Deuda neta de USD 13.7B con ND/EBITDA de 1.9x, mejorada desde pico >4x en FY2023. Deuda total de USD 19.3B con vencimientos escalonados hasta 2032. Equity de USD 8.1B con ROE del 24%."
      },
      {
        "label": "Valuacion",
        "texto": "A USD 12.74 por accion, JBS cotiza a P/E de 7.9x TTM y 7.6x forward, EV/EBITDA de 6.1x y P/FCF de 5.0x. Descuentos del 40-60% vs. peers de alimentos. Upside al precio justo (12-15x EPS fwd) implica potencial del 55-100%."
      },
      {
        "label": "Riesgos principales",
        "texto": "(1) Ciclicidad del ciclo bovino USA con oferta comprimida hasta 2026-2027; (2) Riesgo regulatorio y litigios J&F Leniency activos; (3) Restricciones sanitarias o arancelarias a exportaciones hacia Asia (49% del total exportado); (4) Exposicion cambiaria en portafolio multi-divisa."
      }
    ]
  }
}